{
  "reviews": [
    {
        "id": 1,
        "photo": "https://george-fx.github.io/nuton/users/02.jpg",
        "name": "Lillian Davis",
        "rating": 5,
        "comment": "Lots of good info.",
        "date": "March 3, 2022"
    },
    {
        "id": 2,
        "photo": "https://george-fx.github.io/nuton/users/03.jpg",
        "name": "Adam Thompson",
        "rating": 5,
        "comment": "Great course, Chris helps you get started with a framework where you can then build off of and focus on getting your games.",
        "date": "March 28, 2022"
    },
    {
        "id": 3,
        "photo": "https://george-fx.github.io/nuton/users/04.jpg",
        "name": "Ryan Howard",
        "rating": 5,
        "comment": "It has explained it very well & made it very simple.",
        "date": "February 12, 2022"
    }
  ]
}